README.rst
setup.py
pyevt/__init__.py
pyevt/abi.py
pyevt/ecc.py
pyevt/evt_data.py
pyevt/evt_exception.py
pyevt/libevt.py
pyevt/unit_test.py
pyevt789.egg-info/PKG-INFO
pyevt789.egg-info/SOURCES.txt
pyevt789.egg-info/dependency_links.txt
pyevt789.egg-info/top_level.txt