Metadata-Version: 1.0
Name: pyevt789
Version: 0.0.1
Summary: python interface of evt
Home-page: http://github/everitoken/evt
Author: everiToken
Author-email: everiToken@gmail.com
License: MIT
Platform: UNKNOWN
